iron_cardio/__init__.py
iron_cardio/__main__.py
iron_cardio/console.py
iron_cardio/constants.py
iron_cardio/iron_cardio.py
iron_cardio/iron_cardio_database.py
iron_cardio/iron_cardio_stats.py
iron_cardio-0.1.6.dist-info/LICENSE
iron_cardio-0.1.6.dist-info/METADATA
iron_cardio-0.1.6.dist-info/WHEEL
iron_cardio-0.1.6.dist-info/entry_points.txt
iron_cardio-0.1.6.dist-info/RECORD
