Metadata-Version: 2.1
Name: iron-cardio
Version: 0.1.6
Summary: A CLI tool to create, save, and track progress of Iron Cardio sessions.
Home-page: https://github.com/rhelmstedter/iron-cardio/
Keywords: CLI,kettlebells
Author: Russell Helmstedter
Author-email: rhelmstedter@gmail.com
Requires-Python: >=3.10,<4.0
Classifier: Programming Language :: Python :: 3
Classifier: Programming Language :: Python :: 3.10
Classifier: Programming Language :: Python :: 3.11
Requires-Dist: plotext (>=5.2.8,<6.0.0)
Requires-Dist: rich (>=13.5.2,<14.0.0)
Requires-Dist: typer (>=0.9.0,<0.10.0)
Project-URL: Repository, https://github.com/rhelmstedter/iron-cardio/
